phoenixdatatools/__init__.py
phoenixdatatools/data_analysis.py
phoenixdatatools/data_fake.py
phoenixdatatools/data_quality.py
phoenixdatatools/data_security.py
phoenixdatatools-0.4.4.dist-info/LICENSE
phoenixdatatools-0.4.4.dist-info/METADATA
phoenixdatatools-0.4.4.dist-info/WHEEL
phoenixdatatools-0.4.4.dist-info/RECORD
