Metadata-Version: 2.1
Name: phoenixdatatools
Version: 0.4.4
Summary: Utilities for ready-made Databricks, to shorten and facilitate the development of notebooks and jobs
Author: Indicium
Author-email: leonardo.moretti@indicium.tech
Requires-Python: >=3.9,<4.0
Classifier: Environment :: Console
Classifier: License :: OSI Approved :: MIT License
Classifier: Natural Language :: English
Classifier: Operating System :: OS Independent
Classifier: Programming Language :: Python :: 3
Classifier: Programming Language :: Python :: 3.9
Classifier: Programming Language :: Python :: 3.10
Classifier: Programming Language :: Python :: 3.11
Classifier: Programming Language :: Python :: 3.12
Classifier: Programming Language :: Python :: 3.13
Classifier: Topic :: Scientific/Engineering :: Information Analysis
Classifier: Topic :: Software Development :: Libraries :: Python Modules
Requires-Dist: faker (>=26.2.0,<27.0.0)
Requires-Dist: matplotlib (>=3.9.2,<4.0.0)
Requires-Dist: seaborn (>=0.13.2,<0.14.0)
